README.md
setup.cfg
setup.py
dnsdumpster/API_example.py
dnsdumpster/DNSDumpsterAPI.py
dnsdumpster/__init__.py
dnsdumpster/test_api.py
dnsdumpster.egg-info/PKG-INFO
dnsdumpster.egg-info/SOURCES.txt
dnsdumpster.egg-info/dependency_links.txt
dnsdumpster.egg-info/requires.txt
dnsdumpster.egg-info/top_level.txt