Metadata-Version: 1.1
Name: dnsdumpster
Version: 0.8
Summary: DNS Dumpster lib
Home-page: https://github.com/PaulSec/API-dnsdumpster.com
Author: Paul Sec
Author-email: paulwebsec@gmail.com
License: UNKNOWN
Download-URL: https://github.com/PaulSec/API-dnsdumpster.com/tarball/0.8
Keywords: dnsdumpster,dns,harvesting
Platform: UNKNOWN
